pudzu/dates/__init__.py
pudzu/dates/dates.py
pudzu_dates-0.9.3.dist-info/METADATA
pudzu_dates-0.9.3.dist-info/WHEEL
pudzu_dates-0.9.3.dist-info/RECORD
