Metadata-Version: 2.1
Name: pudzu-dates
Version: 0.9.3
Summary: Date classes supporting flexible calendars, date deltas and ranges
Home-page: https://github.com/Udzu/pudzu-packages/pudzu-dates/
License: MIT
Keywords: pudzu,date,calendar
Author: Uri Granta
Author-email: uri.granta+python@gmail.com
Requires-Python: >=3.7,<4.0
Classifier: License :: OSI Approved :: MIT License
Classifier: Operating System :: OS Independent
Classifier: Programming Language :: Python :: 3
Classifier: Programming Language :: Python :: 3.7
Classifier: Programming Language :: Python :: 3.8
Classifier: Programming Language :: Python :: 3.9
Classifier: Programming Language :: Python :: 3.10
Classifier: Programming Language :: Python :: 3.11
Classifier: Programming Language :: Python :: 3.12
Provides-Extra: extras
Requires-Dist: convertdate (>=2.3.0,<3.0.0) ; extra == "extras"
Requires-Dist: pudzu-utils (>=0.9.3,<0.10.0)
